mellerikat_edge-1.0.6.dist-info/licenses/LICENSE
mellerikatedge/__init__.py
mellerikatedge/cli.py
mellerikatedge/edge_app.py
mellerikatedge/edge_client.py
mellerikatedge/edge_config.py
mellerikatedge/edge_utils.py
mellerikatedge/version.py
mellerikat_edge-1.0.6.dist-info/METADATA
mellerikat_edge-1.0.6.dist-info/WHEEL
mellerikat_edge-1.0.6.dist-info/entry_points.txt
mellerikat_edge-1.0.6.dist-info/top_level.txt
mellerikat_edge-1.0.6.dist-info/RECORD
